hyj_open_api/__init__.py
hyj_open_api/python_auto.py
hyj_open_api/CrawlerUtils/__init__.py
hyj_open_api/CrawlerUtils/web_crawler_api.py
hyj_open_api/excel_pro/__init__.py
hyj_open_api/excel_pro/excel_api.py
hyj_open_api-1.1.2.dist-info/LICENSE
hyj_open_api-1.1.2.dist-info/METADATA
hyj_open_api-1.1.2.dist-info/WHEEL
hyj_open_api-1.1.2.dist-info/top_level.txt
hyj_open_api-1.1.2.dist-info/RECORD
